fastlap-0.1.6.dist-info/METADATA
fastlap-0.1.6.dist-info/WHEEL
fastlap-0.1.6.dist-info/licenses/LICENSE
fastlap/__init__.py
fastlap/fastlap.cpython-39-x86_64-linux-gnu.so
fastlap-0.1.6.dist-info/RECORD
