Metadata-Version: 2.4
Name: fastlap
Version: 0.1.6
Classifier: Programming Language :: Rust
Classifier: Programming Language :: Python :: Implementation :: CPython
Classifier: Programming Language :: Python :: Implementation :: PyPy
Requires-Dist: lap>=0.4.0
Requires-Dist: maturin[patchelf]>=1.8.7
Requires-Dist: numpy>=1.20,<2.0
Requires-Dist: twine>=6.1.0
License-File: LICENSE
Summary: Python’s LAP (Linear Assignment Problem) solver — written in Rust for performance
Keywords: lap,linear assignment problem,hungarian,lapjv,dantzig,auction,subgradient
Home-Page: https://github.com/8Opt/fastlap
Author: Le Duc Minh
Author-email: minh.leduc.0210@gmail.com
Maintainer-email: Le Duc Minh <minh.leduc.0210@gmail.com>
License: MIT
Requires-Python: >=3.8
Project-URL: Source Code, https://github.com/8Opt/fastlap
